Metadata-Version: 2.1
Name: FSlash
Version: 0.17.0
Summary: Practical functional programming for Python 3.8+
Home-page: https://github.com/dbrattli/fslash
Author: Dag Brattli
Author-email: dag@brattli.net
License: MIT License
Download-URL: https://github.com/dbrattli/fslash
Platform: UNKNOWN
Classifier: Development Status :: 3 - Alpha
Classifier: Environment :: Other Environment
Classifier: Intended Audience :: Developers
Classifier: License :: OSI Approved :: MIT License
Classifier: Operating System :: OS Independent
Classifier: Programming Language :: Python :: 3.8
Classifier: Topic :: Software Development :: Libraries :: Python Modules
Requires-Python: >=3.8
